[
  {
    "slug": "alabama",
    "name": "Alabama",
    "code": "AL",
    "wikipediaTitle": "Alabama State Capitol",
    "wikipediaUrl": "https://en.wikipedia.org/wiki/Alabama_State_Capitol",
    "imageUrl": "https://upload.wikimedia.org/wikipedia/commons/f/fc/Alabama_State_Capitol%2C_Montgomery%2C_West_view_20160713_1.jpg",
    "imageWidth": 5348,
    "imageHeight": 4278,
    "mime": "image/jpeg",
    "commonsFileTitle": "File:Alabama State Capitol, Montgomery, West view 20160713 1.jpg",
    "commonsFileUrl": "https://commons.wikimedia.org/wiki/File:Alabama_State_Capitol,_Montgomery,_West_view_20160713_1.jpg",
    "licenseShort": "CC BY-SA 4.0",
    "licenseUrl": "https://creativecommons.org/licenses/by-sa/4.0",
    "artistHtml": "<a href=\"//commons.wikimedia.org/wiki/User:DXR\" title=\"User:DXR\">DXR</a>",
    "artistText": "DXR",
    "avifPath": "/state-images/alabama.avif",
    "jpgPath": "/state-images/alabama.jpg",
    "finalWidth": 1280,
    "finalHeight": 1024,
    "avifBytes": 93170,
    "jpgBytes": 158483
  },
  {
    "slug": "alaska",
    "name": "Alaska",
    "code": "AK",
    "wikipediaTitle": "Alaska State Capitol",
    "wikipediaUrl": "https://en.wikipedia.org/wiki/Alaska_State_Capitol",
    "imageUrl": "https://upload.wikimedia.org/wikipedia/commons/0/07/210103_Snowy_capitol.jpg",
    "imageWidth": 2400,
    "imageHeight": 1472,
    "mime": "image/jpeg",
    "commonsFileTitle": "File:210103 Snowy capitol.jpg",
    "commonsFileUrl": "https://commons.wikimedia.org/wiki/File:210103_Snowy_capitol.jpg",
    "licenseShort": "CC BY 2.0",
    "licenseUrl": "https://creativecommons.org/licenses/by/2.0",
    "artistHtml": "James Brooks",
    "artistText": "James Brooks",
    "avifPath": "/state-images/alaska.avif",
    "jpgPath": "/state-images/alaska.jpg",
    "finalWidth": 1280,
    "finalHeight": 785,
    "avifBytes": 96675,
    "jpgBytes": 158778
  },
  {
    "slug": "arizona",
    "name": "Arizona",
    "code": "AZ",
    "wikipediaTitle": "Arizona State Capitol",
    "wikipediaUrl": "https://en.wikipedia.org/wiki/Arizona_State_Capitol",
    "imageUrl": "https://upload.wikimedia.org/wikipedia/commons/9/9c/Arizona_State_Capitol%2C_Washington_Street_and_17th_Avenue%2C_Phoenix%2C_AZ_-_54441873193.jpg",
    "imageWidth": 3875,
    "imageHeight": 2906,
    "mime": "image/jpeg",
    "commonsFileTitle": "File:Arizona State Capitol, Washington Street and 17th Avenue, Phoenix, AZ - 54441873193.jpg",
    "commonsFileUrl": "https://commons.wikimedia.org/wiki/File:Arizona_State_Capitol,_Washington_Street_and_17th_Avenue,_Phoenix,_AZ_-_54441873193.jpg",
    "licenseShort": "CC BY-SA 2.0",
    "licenseUrl": "https://creativecommons.org/licenses/by-sa/2.0",
    "artistHtml": "w_lemay",
    "artistText": "w_lemay",
    "avifPath": "/state-images/arizona.avif",
    "jpgPath": "/state-images/arizona.jpg",
    "finalWidth": 1280,
    "finalHeight": 960,
    "avifBytes": 111673,
    "jpgBytes": 185171
  },
  {
    "slug": "arkansas",
    "name": "Arkansas",
    "code": "AR",
    "wikipediaTitle": "Arkansas State Capitol",
    "wikipediaUrl": "https://en.wikipedia.org/wiki/Arkansas_State_Capitol",
    "imageUrl": "https://upload.wikimedia.org/wikipedia/commons/6/61/Arkansas_State_Capitol.jpg",
    "imageWidth": 9235,
    "imageHeight": 3708,
    "mime": "image/jpeg",
    "commonsFileTitle": "File:Arkansas State Capitol.jpg",
    "commonsFileUrl": "https://commons.wikimedia.org/wiki/File:Arkansas_State_Capitol.jpg",
    "licenseShort": "CC BY-SA 4.0",
    "licenseUrl": "https://creativecommons.org/licenses/by-sa/4.0",
    "artistHtml": "<a href=\"//commons.wikimedia.org/wiki/User:Dschwen\" title=\"User:Dschwen\">Daniel Schwen</a>",
    "artistText": "Daniel Schwen",
    "avifPath": "/state-images/arkansas.avif",
    "jpgPath": "/state-images/arkansas.jpg",
    "finalWidth": 1280,
    "finalHeight": 514,
    "avifBytes": 40478,
    "jpgBytes": 66543
  },
  {
    "slug": "california",
    "name": "California",
    "code": "CA",
    "wikipediaTitle": "California State Capitol",
    "wikipediaUrl": "https://en.wikipedia.org/wiki/California_State_Capitol",
    "imageUrl": "https://upload.wikimedia.org/wikipedia/commons/5/5a/Sacramento%2C-California---State-Capitol.jpg",
    "imageWidth": 5297,
    "imageHeight": 3642,
    "mime": "image/jpeg",
    "commonsFileTitle": "File:Sacramento,-California---State-Capitol.jpg",
    "commonsFileUrl": "https://commons.wikimedia.org/wiki/File:Sacramento,-California---State-Capitol.jpg",
    "licenseShort": "CC BY-SA 3.0",
    "licenseUrl": "https://creativecommons.org/licenses/by-sa/3.0",
    "artistHtml": "<a href=\"//commons.wikimedia.org/w/index.php?title=User:Andre_m&amp;action=edit&amp;redlink=1\" class=\"new\" title=\"User:Andre m (page does not exist)\">Andre m</a>",
    "artistText": "Andre m",
    "avifPath": "/state-images/california.avif",
    "jpgPath": "/state-images/california.jpg",
    "finalWidth": 1280,
    "finalHeight": 880,
    "avifBytes": 216487,
    "jpgBytes": 249302
  },
  {
    "slug": "colorado",
    "name": "Colorado",
    "code": "CO",
    "wikipediaTitle": "Colorado State Capitol",
    "wikipediaUrl": "https://en.wikipedia.org/wiki/Colorado_State_Capitol",
    "imageUrl": "https://upload.wikimedia.org/wikipedia/commons/5/54/Colorado_State_Capitol_building.jpg",
    "imageWidth": 11651,
    "imageHeight": 7768,
    "mime": "image/jpeg",
    "commonsFileTitle": "File:Colorado State Capitol building.jpg",
    "commonsFileUrl": "https://commons.wikimedia.org/wiki/File:Colorado_State_Capitol_building.jpg",
    "licenseShort": "CC BY 4.0",
    "licenseUrl": "https://creativecommons.org/licenses/by/4.0",
    "artistHtml": "<a href=\"//commons.wikimedia.org/wiki/User:Quintin_Soloviev\" title=\"User:Quintin Soloviev\">Quintin Soloviev</a>",
    "artistText": "Quintin Soloviev",
    "avifPath": "/state-images/colorado.avif",
    "jpgPath": "/state-images/colorado.jpg",
    "finalWidth": 1280,
    "finalHeight": 854,
    "avifBytes": 123054,
    "jpgBytes": 180893
  },
  {
    "slug": "connecticut",
    "name": "Connecticut",
    "code": "CT",
    "wikipediaTitle": "Connecticut State Capitol",
    "wikipediaUrl": "https://en.wikipedia.org/wiki/Connecticut_State_Capitol",
    "imageUrl": "https://upload.wikimedia.org/wikipedia/commons/a/aa/Connecticut_State_Capitol%2C_February_24%2C_2008.jpg",
    "imageWidth": 3664,
    "imageHeight": 2398,
    "mime": "image/jpeg",
    "commonsFileTitle": "File:Connecticut State Capitol, February 24, 2008.jpg",
    "commonsFileUrl": "https://commons.wikimedia.org/wiki/File:Connecticut_State_Capitol,_February_24,_2008.jpg",
    "licenseShort": "CC BY-SA 4.0",
    "licenseUrl": "https://creativecommons.org/licenses/by-sa/4.0",
    "artistHtml": "<a href=\"//commons.wikimedia.org/wiki/User:Ragesoss\" title=\"User:Ragesoss\">Ragesoss</a>",
    "artistText": "Ragesoss",
    "avifPath": "/state-images/connecticut.avif",
    "jpgPath": "/state-images/connecticut.jpg",
    "finalWidth": 1280,
    "finalHeight": 838,
    "avifBytes": 106523,
    "jpgBytes": 152115
  },
  {
    "slug": "delaware",
    "name": "Delaware",
    "code": "DE",
    "wikipediaTitle": "Delaware Legislative Hall",
    "wikipediaUrl": "https://en.wikipedia.org/wiki/Delaware_Legislative_Hall",
    "imageUrl": "https://upload.wikimedia.org/wikipedia/commons/7/79/2022-07-20_08_03_40_The_east_side_of_the_Delaware_Legislative_Hall_%28Delaware_Capitol_Building%29_in_Dover%2C_Kent_County%2C_Delaware.jpg",
    "imageWidth": 4032,
    "imageHeight": 3024,
    "mime": "image/jpeg",
    "commonsFileTitle": "File:2022-07-20 08 03 40 The east side of the Delaware Legislative Hall (Delaware Capitol Building) in Dover, Kent County, Delaware.jpg",
    "commonsFileUrl": "https://commons.wikimedia.org/wiki/File:2022-07-20_08_03_40_The_east_side_of_the_Delaware_Legislative_Hall_(Delaware_Capitol_Building)_in_Dover,_Kent_County,_Delaware.jpg",
    "licenseShort": "CC BY-SA 4.0",
    "licenseUrl": "https://creativecommons.org/licenses/by-sa/4.0",
    "artistHtml": "<a href=\"//commons.wikimedia.org/wiki/User:Famartin\" title=\"User:Famartin\">Famartin</a>",
    "artistText": "Famartin",
    "avifPath": "/state-images/delaware.avif",
    "jpgPath": "/state-images/delaware.jpg",
    "finalWidth": 1280,
    "finalHeight": 960,
    "avifBytes": 144276,
    "jpgBytes": 193485
  },
  {
    "slug": "district-of-columbia",
    "name": "District of Columbia",
    "code": "DC",
    "wikipediaTitle": "United States Capitol",
    "wikipediaUrl": "https://en.wikipedia.org/wiki/United_States_Capitol",
    "imageUrl": "https://upload.wikimedia.org/wikipedia/commons/2/27/Capitol_Building_Full_View.jpg",
    "imageWidth": 7168,
    "imageHeight": 3072,
    "mime": "image/jpeg",
    "commonsFileTitle": "File:Capitol Building Full View.jpg",
    "commonsFileUrl": "https://commons.wikimedia.org/wiki/File:Capitol_Building_Full_View.jpg",
    "licenseShort": "Public domain",
    "licenseUrl": null,
    "artistHtml": "<a href=\"https://en.wikipedia.org/wiki/User:Noclip\" class=\"extiw\" title=\"en:User:Noclip\">Noclip</a>",
    "artistText": "Noclip",
    "avifPath": "/state-images/district-of-columbia.avif",
    "jpgPath": "/state-images/district-of-columbia.jpg",
    "finalWidth": 1280,
    "finalHeight": 549,
    "avifBytes": 46181,
    "jpgBytes": 74992
  },
  {
    "slug": "florida",
    "name": "Florida",
    "code": "FL",
    "wikipediaTitle": "Florida State Capitol",
    "wikipediaUrl": "https://en.wikipedia.org/wiki/Florida_State_Capitol",
    "imageUrl": "https://upload.wikimedia.org/wikipedia/commons/e/e9/Old_and_New_Florida_State_Capitol%2C_Tallahassee%2C_East_view_20160711_1.jpg",
    "imageWidth": 4528,
    "imageHeight": 6410,
    "mime": "image/jpeg",
    "commonsFileTitle": "File:Old and New Florida State Capitol, Tallahassee, East view 20160711 1.jpg",
    "commonsFileUrl": "https://commons.wikimedia.org/wiki/File:Old_and_New_Florida_State_Capitol,_Tallahassee,_East_view_20160711_1.jpg",
    "licenseShort": "CC BY-SA 4.0",
    "licenseUrl": "https://creativecommons.org/licenses/by-sa/4.0",
    "artistHtml": "<a href=\"//commons.wikimedia.org/wiki/User:DXR\" title=\"User:DXR\">DXR</a>",
    "artistText": "DXR",
    "avifPath": "/state-images/florida.avif",
    "jpgPath": "/state-images/florida.jpg",
    "finalWidth": 904,
    "finalHeight": 1280,
    "avifBytes": 80726,
    "jpgBytes": 133118
  },
  {
    "slug": "georgia",
    "name": "Georgia",
    "code": "GA",
    "wikipediaTitle": "Georgia State Capitol",
    "wikipediaUrl": "https://en.wikipedia.org/wiki/Georgia_State_Capitol",
    "imageUrl": "https://upload.wikimedia.org/wikipedia/commons/d/dc/Georgia_State_Capitol%2C_Atlanta%2C_West_view_20160716_1.jpg",
    "imageWidth": 6093,
    "imageHeight": 3949,
    "mime": "image/jpeg",
    "commonsFileTitle": "File:Georgia State Capitol, Atlanta, West view 20160716 1.jpg",
    "commonsFileUrl": "https://commons.wikimedia.org/wiki/File:Georgia_State_Capitol,_Atlanta,_West_view_20160716_1.jpg",
    "licenseShort": "CC BY-SA 4.0",
    "licenseUrl": "https://creativecommons.org/licenses/by-sa/4.0",
    "artistHtml": "<a href=\"//commons.wikimedia.org/wiki/User:DXR\" title=\"User:DXR\">DXR</a>",
    "artistText": "DXR",
    "avifPath": "/state-images/georgia.avif",
    "jpgPath": "/state-images/georgia.jpg",
    "finalWidth": 1280,
    "finalHeight": 830,
    "avifBytes": 117893,
    "jpgBytes": 167894
  },
  {
    "slug": "hawaii",
    "name": "Hawaii",
    "code": "HI",
    "wikipediaTitle": "Hawaii State Capitol",
    "wikipediaUrl": "https://en.wikipedia.org/wiki/Hawaii_State_Capitol",
    "imageUrl": "https://upload.wikimedia.org/wikipedia/commons/5/5b/Hawaii_state_capitol_from_the_south-east.jpg",
    "imageWidth": 1600,
    "imageHeight": 1200,
    "mime": "image/jpeg",
    "commonsFileTitle": "File:Hawaii state capitol from the south-east.jpg",
    "commonsFileUrl": "https://commons.wikimedia.org/wiki/File:Hawaii_state_capitol_from_the_south-east.jpg",
    "licenseShort": "Public domain",
    "licenseUrl": null,
    "artistHtml": "<p><a href=\"//commons.wikimedia.org/w/index.php?title=User:Xpixupload&amp;action=edit&amp;redlink=1\" class=\"new\" title=\"User:Xpixupload (page does not exist)\">Xpixupload</a>\n</p>\n<table class=\"toccolours layouttemplate commons-file-information-table\" style=\"width: 100%;\" dir=\"ltr\" lang=\"en\">\n<tbody><tr><th class=\"type fileinfo-paramfield\">Camera location</th><td style=\"border:none;\"><span class=\"plainlinks\"><span class=\"plainlinksneverexpand\"><a class=\"external text\" href=\"https://geohack.toolforge.org/geohack.php?pagename=File:Hawaii_state_capitol_from_the_south-east.jpg&amp;params=021.306760_N_-157.857370_E_globe:Earth_type:camera__&amp;language=en\">21° 18′ 24.34″ N, 157° 51′ 26.53″ W</a></span></span> <a class=\"mw-kartographer-maplink no-icon\" data-mw-kartographer=\"maplink\" data-style=\"osm-intl\" href=\"//commons.wikimedia.org/wiki/Special:Map/13/21.30676/-157.85737/en\" data-zoom=\"13\" data-lat=\"21.30676\" data-lon=\"-157.85737\" data-overlays='[\"_7aac4d27cd57c1f1e1846ba90061eb66e9475496\"]'><span typeof=\"mw:File\"><span title=\"Kartographer map based on OpenStreetMap.\"><img alt=\"Kartographer map based on OpenStreetMap.\" src=\"https://upload.wikimedia.org/wikipedia/commons/thumb/b/b0/Openstreetmap_logo.svg/20px-Openstreetmap_logo.svg.png\" decoding=\"async\" width=\"20\" height=\"20\" class=\"mw-file-element\" srcset=\"https://upload.wikimedia.org/wikipedia/commons/thumb/b/b0/Openstreetmap_logo.svg/40px-Openstreetmap_logo.svg.png 2x\" data-file-width=\"256\" data-file-height=\"256\"></span></span></a></td><td style=\"border:none;\">View this and other nearby images on: <a class=\"external text\" href=\"https://wikimap.toolforge.org/?wp=false&amp;cluster=false&amp;zoom=16&amp;lat=021.306760&amp;lon=-157.857370\">OpenStreetMap</a></td><td style=\"border:none;\"><span class=\"skin-invert\" typeof=\"mw:File\"><a href=\"//commons.wikimedia.org/wiki/Commons:Geocoding\" title=\"Commons:Geocoding\"><img alt=\"info\" src=\"https://upload.wikimedia.org/wikipedia/commons/thumb/6/69/OOjs_UI_icon_help.svg/20px-OOjs_UI_icon_help.svg.png\" decoding=\"async\" width=\"18\" height=\"18\" class=\"mw-file-element\" srcset=\"https://upload.wikimedia.org/wikipedia/commons/thumb/6/69/OOjs_UI_icon_help.svg/40px-OOjs_UI_icon_help.svg.png 2x\" data-file-width=\"24\" data-file-height=\"24\"></a></span><span class=\"geo\" style=\"display:none\"> 21.306760; -157.857370</span></td></tr>\n</tbody></table>",
    "artistText": "Xpixupload Camera location21° 18′ 24.34″ N, 157° 51′ 26.53″ W View this and other nearby images on: OpenStreetMap 21.306760; -157.857370",
    "avifPath": "/state-images/hawaii.avif",
    "jpgPath": "/state-images/hawaii.jpg",
    "finalWidth": 1280,
    "finalHeight": 960,
    "avifBytes": 109150,
    "jpgBytes": 175314
  },
  {
    "slug": "idaho",
    "name": "Idaho",
    "code": "ID",
    "wikipediaTitle": "Idaho State Capitol",
    "wikipediaUrl": "https://en.wikipedia.org/wiki/Idaho_State_Capitol",
    "imageUrl": "https://upload.wikimedia.org/wikipedia/commons/5/59/Idaho_State_Capitol_building.jpg",
    "imageWidth": 3796,
    "imageHeight": 2531,
    "mime": "image/jpeg",
    "commonsFileTitle": "File:Idaho State Capitol building.jpg",
    "commonsFileUrl": "https://commons.wikimedia.org/wiki/File:Idaho_State_Capitol_building.jpg",
    "licenseShort": "CC BY 4.0",
    "licenseUrl": "https://creativecommons.org/licenses/by/4.0",
    "artistHtml": "<a href=\"//commons.wikimedia.org/wiki/User:Quintin_Soloviev\" title=\"User:Quintin Soloviev\">Quintin Soloviev</a>",
    "artistText": "Quintin Soloviev",
    "avifPath": "/state-images/idaho.avif",
    "jpgPath": "/state-images/idaho.jpg",
    "finalWidth": 1280,
    "finalHeight": 853,
    "avifBytes": 116399,
    "jpgBytes": 160059
  },
  {
    "slug": "illinois",
    "name": "Illinois",
    "code": "IL",
    "wikipediaTitle": "Illinois State Capitol",
    "wikipediaUrl": "https://en.wikipedia.org/wiki/Illinois_State_Capitol",
    "imageUrl": "https://upload.wikimedia.org/wikipedia/commons/d/d1/Illinois_State_Capitol_pano.jpg",
    "imageWidth": 5000,
    "imageHeight": 3970,
    "mime": "image/jpeg",
    "commonsFileTitle": "File:Illinois State Capitol pano.jpg",
    "commonsFileUrl": "https://commons.wikimedia.org/wiki/File:Illinois_State_Capitol_pano.jpg",
    "licenseShort": "CC BY-SA 4.0",
    "licenseUrl": "https://creativecommons.org/licenses/by-sa/4.0",
    "artistHtml": "<a href=\"//commons.wikimedia.org/wiki/User:Dschwen\" title=\"User:Dschwen\">Daniel Schwen</a>",
    "artistText": "Daniel Schwen",
    "avifPath": "/state-images/illinois.avif",
    "jpgPath": "/state-images/illinois.jpg",
    "finalWidth": 1280,
    "finalHeight": 1016,
    "avifBytes": 95932,
    "jpgBytes": 139913
  },
  {
    "slug": "indiana",
    "name": "Indiana",
    "code": "IN",
    "wikipediaTitle": "Indiana Statehouse",
    "wikipediaUrl": "https://en.wikipedia.org/wiki/Indiana_Statehouse",
    "imageUrl": "https://upload.wikimedia.org/wikipedia/commons/f/fe/StateCapitolIndiana.jpg",
    "imageWidth": 3772,
    "imageHeight": 2652,
    "mime": "image/jpeg",
    "commonsFileTitle": "File:StateCapitolIndiana.jpg",
    "commonsFileUrl": "https://commons.wikimedia.org/wiki/File:StateCapitolIndiana.jpg",
    "licenseShort": "CC BY-SA 3.0",
    "licenseUrl": "http://creativecommons.org/licenses/by-sa/3.0/",
    "artistHtml": "Original: <a href=\"//commons.wikimedia.org/wiki/User:Dschwen\" title=\"User:Dschwen\">Daniel Schwen</a><br>Derivative work: <a href=\"//commons.wikimedia.org/wiki/User:Massimo_Catarinella\" title=\"User:Massimo Catarinella\">Massimo Catarinella</a>",
    "artistText": "Original: Daniel SchwenDerivative work: Massimo Catarinella",
    "avifPath": "/state-images/indiana.avif",
    "jpgPath": "/state-images/indiana.jpg",
    "finalWidth": 1280,
    "finalHeight": 900,
    "avifBytes": 102315,
    "jpgBytes": 154477
  },
  {
    "slug": "iowa",
    "name": "Iowa",
    "code": "IA",
    "wikipediaTitle": "Iowa State Capitol",
    "wikipediaUrl": "https://en.wikipedia.org/wiki/Iowa_State_Capitol",
    "imageUrl": "https://upload.wikimedia.org/wikipedia/commons/1/12/Capitol_building%2C_Des_Moines%2C_Iowa.jpg",
    "imageWidth": 1024,
    "imageHeight": 798,
    "mime": "image/jpeg",
    "commonsFileTitle": "File:Capitol building, Des Moines, Iowa.jpg",
    "commonsFileUrl": "https://commons.wikimedia.org/wiki/File:Capitol_building,_Des_Moines,_Iowa.jpg",
    "licenseShort": "Public domain",
    "licenseUrl": null,
    "artistHtml": "<bdi><a href=\"https://en.wikipedia.org/wiki/en:Carol_M._Highsmith\" class=\"extiw\" title=\"w:en:Carol M. Highsmith\"><span title=\"American photographer (born 1946)\">Carol M. Highsmith</span></a></bdi>",
    "artistText": "Carol M. Highsmith",
    "avifPath": "/state-images/iowa.avif",
    "jpgPath": "/state-images/iowa.jpg",
    "finalWidth": 1024,
    "finalHeight": 798,
    "avifBytes": 87814,
    "jpgBytes": 125788
  },
  {
    "slug": "kansas",
    "name": "Kansas",
    "code": "KS",
    "wikipediaTitle": "Kansas State Capitol",
    "wikipediaUrl": "https://en.wikipedia.org/wiki/Kansas_State_Capitol",
    "imageUrl": "https://upload.wikimedia.org/wikipedia/commons/0/08/Kansas_State_Capitol_in_summer_2024.jpg",
    "imageWidth": 7008,
    "imageHeight": 4672,
    "mime": "image/jpeg",
    "commonsFileTitle": "File:Kansas State Capitol in summer 2024.jpg",
    "commonsFileUrl": "https://commons.wikimedia.org/wiki/File:Kansas_State_Capitol_in_summer_2024.jpg",
    "licenseShort": "CC BY 4.0",
    "licenseUrl": "https://creativecommons.org/licenses/by/4.0",
    "artistHtml": "Nils Huenerfuerst",
    "artistText": "Nils Huenerfuerst",
    "avifPath": "/state-images/kansas.avif",
    "jpgPath": "/state-images/kansas.jpg",
    "finalWidth": 1280,
    "finalHeight": 853,
    "avifBytes": 179222,
    "jpgBytes": 217825
  },
  {
    "slug": "kentucky",
    "name": "Kentucky",
    "code": "KY",
    "wikipediaTitle": "Kentucky State Capitol",
    "wikipediaUrl": "https://en.wikipedia.org/wiki/Kentucky_State_Capitol",
    "imageUrl": "https://upload.wikimedia.org/wikipedia/commons/6/6e/U.S._Route_60_Frankfort%2C_KY_%2823892062134%29.jpg",
    "imageWidth": 4640,
    "imageHeight": 2610,
    "mime": "image/jpeg",
    "commonsFileTitle": "File:U.S. Route 60 Frankfort, KY (23892062134).jpg",
    "commonsFileUrl": "https://commons.wikimedia.org/wiki/File:U.S._Route_60_Frankfort,_KY_(23892062134).jpg",
    "licenseShort": "CC BY-SA 2.0",
    "licenseUrl": "https://creativecommons.org/licenses/by-sa/2.0",
    "artistHtml": "<a rel=\"nofollow\" class=\"external text\" href=\"https://www.flickr.com/people/52257493@N00\">Mobilus In Mobili</a>",
    "artistText": "Mobilus In Mobili",
    "avifPath": "/state-images/kentucky.avif",
    "jpgPath": "/state-images/kentucky.jpg",
    "finalWidth": 1280,
    "finalHeight": 720,
    "avifBytes": 213092,
    "jpgBytes": 226501
  },
  {
    "slug": "louisiana",
    "name": "Louisiana",
    "code": "LA",
    "wikipediaTitle": "Louisiana State Capitol",
    "wikipediaUrl": "https://en.wikipedia.org/wiki/Louisiana_State_Capitol",
    "imageUrl": "https://upload.wikimedia.org/wikipedia/commons/5/50/Louisiana_State_Capitol_Building.jpg",
    "imageWidth": 11753,
    "imageHeight": 12708,
    "mime": "image/jpeg",
    "commonsFileTitle": "File:Louisiana State Capitol Building.jpg",
    "commonsFileUrl": "https://commons.wikimedia.org/wiki/File:Louisiana_State_Capitol_Building.jpg",
    "licenseShort": "CC0",
    "licenseUrl": "http://creativecommons.org/publicdomain/zero/1.0/deed.en",
    "artistHtml": "<a href=\"//commons.wikimedia.org/w/index.php?title=User:Chrismiceli&amp;action=edit&amp;redlink=1\" class=\"new\" title=\"User:Chrismiceli (page does not exist)\">Chrismiceli</a>",
    "artistText": "Chrismiceli",
    "avifPath": "/state-images/louisiana.avif",
    "jpgPath": "/state-images/louisiana.jpg",
    "finalWidth": 1184,
    "finalHeight": 1280,
    "avifBytes": 54856,
    "jpgBytes": 138187
  },
  {
    "slug": "maine",
    "name": "Maine",
    "code": "ME",
    "wikipediaTitle": "Maine State House",
    "wikipediaUrl": "https://en.wikipedia.org/wiki/Maine_State_House",
    "imageUrl": "https://upload.wikimedia.org/wikipedia/commons/6/64/Maine_State_House_exterior_view_%28cropped%29.jpg",
    "imageWidth": 6394,
    "imageHeight": 4450,
    "mime": "image/jpeg",
    "commonsFileTitle": "File:Maine State House exterior view (cropped).jpg",
    "commonsFileUrl": "https://commons.wikimedia.org/wiki/File:Maine_State_House_exterior_view_(cropped).jpg",
    "licenseShort": "CC BY 4.0",
    "licenseUrl": "https://creativecommons.org/licenses/by/4.0",
    "artistHtml": "<a href=\"//commons.wikimedia.org/wiki/User:Quintinsoloviev\" class=\"mw-redirect\" title=\"User:Quintinsoloviev\">Quintin Soloviev</a>",
    "artistText": "Quintin Soloviev",
    "avifPath": "/state-images/maine.avif",
    "jpgPath": "/state-images/maine.jpg",
    "finalWidth": 1280,
    "finalHeight": 891,
    "avifBytes": 167269,
    "jpgBytes": 212316
  },
  {
    "slug": "maryland",
    "name": "Maryland",
    "code": "MD",
    "wikipediaTitle": "Maryland State House",
    "wikipediaUrl": "https://en.wikipedia.org/wiki/Maryland_State_House",
    "imageUrl": "https://upload.wikimedia.org/wikipedia/commons/0/06/Maryland_State_House_from_College_Ave.JPG",
    "imageWidth": 3631,
    "imageHeight": 3071,
    "mime": "image/jpeg",
    "commonsFileTitle": "File:Maryland State House from College Ave.JPG",
    "commonsFileUrl": "https://commons.wikimedia.org/wiki/File:Maryland_State_House_from_College_Ave.JPG",
    "licenseShort": "CC BY-SA 3.0",
    "licenseUrl": "https://creativecommons.org/licenses/by-sa/3.0",
    "artistHtml": "<a href=\"//commons.wikimedia.org/wiki/User:Martin_Falbisoner\" title=\"User:Martin Falbisoner\">Martin Falbisoner</a>",
    "artistText": "Martin Falbisoner",
    "avifPath": "/state-images/maryland.avif",
    "jpgPath": "/state-images/maryland.jpg",
    "finalWidth": 1280,
    "finalHeight": 1083,
    "avifBytes": 163601,
    "jpgBytes": 210692
  },
  {
    "slug": "massachusetts",
    "name": "Massachusetts",
    "code": "MA",
    "wikipediaTitle": "Massachusetts State House",
    "wikipediaUrl": "https://en.wikipedia.org/wiki/Massachusetts_State_House",
    "imageUrl": "https://upload.wikimedia.org/wikipedia/commons/9/90/Massachusetts_State_House_Boston_November_2016.jpg",
    "imageWidth": 5200,
    "imageHeight": 3120,
    "mime": "image/jpeg",
    "commonsFileTitle": "File:Massachusetts State House Boston November 2016.jpg",
    "commonsFileUrl": "https://commons.wikimedia.org/wiki/File:Massachusetts_State_House_Boston_November_2016.jpg",
    "licenseShort": "CC BY-SA 4.0",
    "licenseUrl": "https://creativecommons.org/licenses/by-sa/4.0",
    "artistHtml": "<a href=\"//commons.wikimedia.org/wiki/User:King_of_Hearts\" title=\"User:King of Hearts\">King of Hearts</a>",
    "artistText": "King of Hearts",
    "avifPath": "/state-images/massachusetts.avif",
    "jpgPath": "/state-images/massachusetts.jpg",
    "finalWidth": 1280,
    "finalHeight": 768,
    "avifBytes": 78654,
    "jpgBytes": 133428
  },
  {
    "slug": "michigan",
    "name": "Michigan",
    "code": "MI",
    "wikipediaTitle": "Michigan State Capitol",
    "wikipediaUrl": "https://en.wikipedia.org/wiki/Michigan_State_Capitol",
    "imageUrl": "https://upload.wikimedia.org/wikipedia/commons/7/71/Michigan_State_Capitol_2024.jpg",
    "imageWidth": 3817,
    "imageHeight": 2268,
    "mime": "image/jpeg",
    "commonsFileTitle": "File:Michigan State Capitol 2024.jpg",
    "commonsFileUrl": "https://commons.wikimedia.org/wiki/File:Michigan_State_Capitol_2024.jpg",
    "licenseShort": "CC BY-SA 4.0",
    "licenseUrl": "https://creativecommons.org/licenses/by-sa/4.0",
    "artistHtml": "<a href=\"//commons.wikimedia.org/wiki/User:Mojnsen\" title=\"User:Mojnsen\">Mojnsen</a>",
    "artistText": "Mojnsen",
    "avifPath": "/state-images/michigan.avif",
    "jpgPath": "/state-images/michigan.jpg",
    "finalWidth": 1280,
    "finalHeight": 761,
    "avifBytes": 138758,
    "jpgBytes": 185695
  },
  {
    "slug": "minnesota",
    "name": "Minnesota",
    "code": "MN",
    "wikipediaTitle": "Minnesota State Capitol",
    "wikipediaUrl": "https://en.wikipedia.org/wiki/Minnesota_State_Capitol",
    "imageUrl": "https://upload.wikimedia.org/wikipedia/commons/5/59/State_Capitol_with_new_Minnesota_State_Flag_11.jpg",
    "imageWidth": 5184,
    "imageHeight": 3456,
    "mime": "image/jpeg",
    "commonsFileTitle": "File:State Capitol with new Minnesota State Flag 11.jpg",
    "commonsFileUrl": "https://commons.wikimedia.org/wiki/File:State_Capitol_with_new_Minnesota_State_Flag_11.jpg",
    "licenseShort": "CC BY 4.0",
    "licenseUrl": "https://creativecommons.org/licenses/by/4.0",
    "artistHtml": "<a href=\"//commons.wikimedia.org/wiki/User:Myotus\" title=\"User:Myotus\">Myotus</a>",
    "artistText": "Myotus",
    "avifPath": "/state-images/minnesota.avif",
    "jpgPath": "/state-images/minnesota.jpg",
    "finalWidth": 1280,
    "finalHeight": 853,
    "avifBytes": 75423,
    "jpgBytes": 133192
  },
  {
    "slug": "mississippi",
    "name": "Mississippi",
    "code": "MS",
    "wikipediaTitle": "Mississippi State Capitol",
    "wikipediaUrl": "https://en.wikipedia.org/wiki/Mississippi_State_Capitol",
    "imageUrl": "https://upload.wikimedia.org/wikipedia/commons/2/28/Mississippi_State_Capitol_%2854893700836%29.jpg",
    "imageWidth": 8192,
    "imageHeight": 5464,
    "mime": "image/jpeg",
    "commonsFileTitle": "File:Mississippi State Capitol (54893700836).jpg",
    "commonsFileUrl": "https://commons.wikimedia.org/wiki/File:Mississippi_State_Capitol_(54893700836).jpg",
    "licenseShort": "CC BY-SA 4.0",
    "licenseUrl": "https://creativecommons.org/licenses/by-sa/4.0",
    "artistHtml": "<a rel=\"nofollow\" class=\"external text\" href=\"https://www.flickr.com/people/22007612@N05\">Gage Skidmore</a> from Surprise, AZ, United States of America",
    "artistText": "Gage Skidmore from Surprise, AZ, United States of America",
    "avifPath": "/state-images/mississippi.avif",
    "jpgPath": "/state-images/mississippi.jpg",
    "finalWidth": 1280,
    "finalHeight": 854,
    "avifBytes": 118313,
    "jpgBytes": 160710
  },
  {
    "slug": "missouri",
    "name": "Missouri",
    "code": "MO",
    "wikipediaTitle": "Missouri State Capitol",
    "wikipediaUrl": "https://en.wikipedia.org/wiki/Missouri_State_Capitol",
    "imageUrl": "https://upload.wikimedia.org/wikipedia/commons/6/68/MissouriCapitol.jpg",
    "imageWidth": 1600,
    "imageHeight": 913,
    "mime": "image/jpeg",
    "commonsFileTitle": "File:MissouriCapitol.jpg",
    "commonsFileUrl": "https://commons.wikimedia.org/wiki/File:MissouriCapitol.jpg",
    "licenseShort": "CC BY-SA 3.0",
    "licenseUrl": "https://creativecommons.org/licenses/by-sa/3.0",
    "artistHtml": "<a href=\"https://en.wikipedia.org/wiki/User:RebelAt\" class=\"extiw\" title=\"en:User:RebelAt\">RebelAt</a> of <a href=\"https://en.wikipedia.org/wiki/Main_Page\" class=\"extiw\" title=\"en:Main Page\">English Wikipedia</a>",
    "artistText": "RebelAt of English Wikipedia",
    "avifPath": "/state-images/missouri.avif",
    "jpgPath": "/state-images/missouri.jpg",
    "finalWidth": 1280,
    "finalHeight": 730,
    "avifBytes": 62566,
    "jpgBytes": 119581
  },
  {
    "slug": "montana",
    "name": "Montana",
    "code": "MT",
    "wikipediaTitle": "Montana State Capitol",
    "wikipediaUrl": "https://en.wikipedia.org/wiki/Montana_State_Capitol",
    "imageUrl": "https://upload.wikimedia.org/wikipedia/commons/8/85/MK01799_Montana_State_Capitol.jpg",
    "imageWidth": 2487,
    "imageHeight": 1728,
    "mime": "image/jpeg",
    "commonsFileTitle": "File:MK01799 Montana State Capitol.jpg",
    "commonsFileUrl": "https://commons.wikimedia.org/wiki/File:MK01799_Montana_State_Capitol.jpg",
    "licenseShort": "CC BY-SA 3.0",
    "licenseUrl": "https://creativecommons.org/licenses/by-sa/3.0",
    "artistHtml": "<a href=\"//commons.wikimedia.org/wiki/User:Martin_Kraft\" title=\"User:Martin Kraft\">Martin Kraft</a>",
    "artistText": "Martin Kraft",
    "avifPath": "/state-images/montana.avif",
    "jpgPath": "/state-images/montana.jpg",
    "finalWidth": 1280,
    "finalHeight": 889,
    "avifBytes": 107311,
    "jpgBytes": 152877
  },
  {
    "slug": "nebraska",
    "name": "Nebraska",
    "code": "NE",
    "wikipediaTitle": "Nebraska State Capitol",
    "wikipediaUrl": "https://en.wikipedia.org/wiki/Nebraska_State_Capitol",
    "imageUrl": "https://upload.wikimedia.org/wikipedia/commons/c/c7/Capitol_building_Lincoln%2C_Nebraska_LCCN2010630796.tif",
    "imageWidth": 6702,
    "imageHeight": 5362,
    "mime": "image/tiff",
    "commonsFileTitle": "File:Capitol building Lincoln, Nebraska LCCN2010630796.tif",
    "commonsFileUrl": "https://commons.wikimedia.org/wiki/File:Capitol_building_Lincoln,_Nebraska_LCCN2010630796.tif",
    "licenseShort": "Public domain",
    "licenseUrl": null,
    "artistHtml": "<bdi><a href=\"https://en.wikipedia.org/wiki/en:Carol_M._Highsmith\" class=\"extiw\" title=\"w:en:Carol M. Highsmith\"><span title=\"American photographer (born 1946)\">Carol M. Highsmith</span></a></bdi>",
    "artistText": "Carol M. Highsmith",
    "avifPath": "/state-images/nebraska.avif",
    "jpgPath": "/state-images/nebraska.jpg",
    "finalWidth": 1280,
    "finalHeight": 1024,
    "avifBytes": 81337,
    "jpgBytes": 144238
  },
  {
    "slug": "nevada",
    "name": "Nevada",
    "code": "NV",
    "wikipediaTitle": "Nevada State Capitol",
    "wikipediaUrl": "https://en.wikipedia.org/wiki/Nevada_State_Capitol",
    "imageUrl": "https://upload.wikimedia.org/wikipedia/commons/9/9d/Nevada_State_Capitol_Building_-_Carson_City.jpg",
    "imageWidth": 7584,
    "imageHeight": 5613,
    "mime": "image/jpeg",
    "commonsFileTitle": "File:Nevada State Capitol Building - Carson City.jpg",
    "commonsFileUrl": "https://commons.wikimedia.org/wiki/File:Nevada_State_Capitol_Building_-_Carson_City.jpg",
    "licenseShort": "CC0",
    "licenseUrl": "http://creativecommons.org/publicdomain/zero/1.0/deed.en",
    "artistHtml": "<a href=\"//commons.wikimedia.org/wiki/User:Quintinsoloviev\" class=\"mw-redirect\" title=\"User:Quintinsoloviev\">Quintin Soloviev</a>",
    "artistText": "Quintin Soloviev",
    "avifPath": "/state-images/nevada.avif",
    "jpgPath": "/state-images/nevada.jpg",
    "finalWidth": 1280,
    "finalHeight": 947,
    "avifBytes": 205952,
    "jpgBytes": 241340
  },
  {
    "slug": "new-hampshire",
    "name": "New Hampshire",
    "code": "NH",
    "wikipediaTitle": "New Hampshire State House",
    "wikipediaUrl": "https://en.wikipedia.org/wiki/New_Hampshire_State_House",
    "imageUrl": "https://upload.wikimedia.org/wikipedia/commons/3/33/New_Hampshire_State_House.jpg",
    "imageWidth": 4892,
    "imageHeight": 3261,
    "mime": "image/jpeg",
    "commonsFileTitle": "File:New Hampshire State House.jpg",
    "commonsFileUrl": "https://commons.wikimedia.org/wiki/File:New_Hampshire_State_House.jpg",
    "licenseShort": "CC BY 4.0",
    "licenseUrl": "https://creativecommons.org/licenses/by/4.0",
    "artistHtml": "<a href=\"//commons.wikimedia.org/wiki/User:Quintin_Soloviev\" title=\"User:Quintin Soloviev\">Quintin Soloviev</a>",
    "artistText": "Quintin Soloviev",
    "avifPath": "/state-images/new-hampshire.avif",
    "jpgPath": "/state-images/new-hampshire.jpg",
    "finalWidth": 1280,
    "finalHeight": 853,
    "avifBytes": 94000,
    "jpgBytes": 138255
  },
  {
    "slug": "new-jersey",
    "name": "New Jersey",
    "code": "NJ",
    "wikipediaTitle": "New Jersey State House",
    "wikipediaUrl": "https://en.wikipedia.org/wiki/New_Jersey_State_House",
    "imageUrl": "https://upload.wikimedia.org/wikipedia/commons/d/d2/New_Jersey_State_House_-_2_%2855141979306%29.jpg",
    "imageWidth": 9018,
    "imageHeight": 5073,
    "mime": "image/jpeg",
    "commonsFileTitle": "File:New Jersey State House - 2 (55141979306).jpg",
    "commonsFileUrl": "https://commons.wikimedia.org/wiki/File:New_Jersey_State_House_-_2_(55141979306).jpg",
    "licenseShort": "CC BY 4.0",
    "licenseUrl": "https://creativecommons.org/licenses/by/4.0",
    "artistHtml": "<a rel=\"nofollow\" class=\"external text\" href=\"https://www.flickr.com/people/83136374@N05\">ajay_suresh</a>",
    "artistText": "ajay_suresh",
    "avifPath": "/state-images/new-jersey.avif",
    "jpgPath": "/state-images/new-jersey.jpg",
    "finalWidth": 1280,
    "finalHeight": 720,
    "avifBytes": 68867,
    "jpgBytes": 111347
  },
  {
    "slug": "new-mexico",
    "name": "New Mexico",
    "code": "NM",
    "wikipediaTitle": "New Mexico State Capitol",
    "wikipediaUrl": "https://en.wikipedia.org/wiki/New_Mexico_State_Capitol",
    "imageUrl": "https://upload.wikimedia.org/wikipedia/commons/c/c5/New_Mexico_State_Capitol.jpg",
    "imageWidth": 4016,
    "imageHeight": 1947,
    "mime": "image/jpeg",
    "commonsFileTitle": "File:New Mexico State Capitol.jpg",
    "commonsFileUrl": "https://commons.wikimedia.org/wiki/File:New_Mexico_State_Capitol.jpg",
    "licenseShort": "CC BY 2.0",
    "licenseUrl": "https://creativecommons.org/licenses/by/2.0",
    "artistHtml": "Jim Bowen",
    "artistText": "Jim Bowen",
    "avifPath": "/state-images/new-mexico.avif",
    "jpgPath": "/state-images/new-mexico.jpg",
    "finalWidth": 1280,
    "finalHeight": 620,
    "avifBytes": 156126,
    "jpgBytes": 177019
  },
  {
    "slug": "new-york",
    "name": "New York",
    "code": "NY",
    "wikipediaTitle": "New York State Capitol",
    "wikipediaUrl": "https://en.wikipedia.org/wiki/New_York_State_Capitol",
    "imageUrl": "https://upload.wikimedia.org/wikipedia/commons/4/42/NYSCapitolPanorama.jpg",
    "imageWidth": 4758,
    "imageHeight": 2825,
    "mime": "image/jpeg",
    "commonsFileTitle": "File:NYSCapitolPanorama.jpg",
    "commonsFileUrl": "https://commons.wikimedia.org/wiki/File:NYSCapitolPanorama.jpg",
    "licenseShort": "CC BY 3.0",
    "licenseUrl": "https://creativecommons.org/licenses/by/3.0",
    "artistHtml": "<table style=\"background-color:##ccf; border:2px solid #A9A9A9; width: 100%; margin:auto; text-align:center;\" align=\"center\" cellspacing=\"8\">\n\n<tbody><tr>\n<td><figure class=\"mw-halign-left\" typeof=\"mw:File\"><a href=\"https://en.wikipedia.org/wiki/User:MattWade/ImageAttribution\" title=\"en:User:MattWade/ImageAttribution\"><img src=\"https://upload.wikimedia.org/wikipedia/commons/thumb/5/5e/Matt_Wade_Photography.svg/250px-Matt_Wade_Photography.svg.png\" decoding=\"async\" width=\"200\" height=\"77\" class=\"mw-file-element\" srcset=\"https://upload.wikimedia.org/wikipedia/commons/thumb/5/5e/Matt_Wade_Photography.svg/500px-Matt_Wade_Photography.svg.png 2x\" data-file-width=\"730\" data-file-height=\"280\"></a><figcaption></figcaption></figure>\n</td>\n<td><big>This image or media was taken or created by <b><a href=\"//commons.wikimedia.org/wiki/User:MattWade\" title=\"User:MattWade\">Matt H. Wade</a></b>. To see his entire portfolio, <a href=\"//commons.wikimedia.org/wiki/Category:Images_by_MattWade\" title=\"Category:Images by MattWade\">click here</a>.<br>@<a rel=\"nofollow\" class=\"external text\" href=\"https://twitter.com/thatmattwade\">thatmattwade</a></big><br>\n<hr><br>\n<p><span typeof=\"mw:File\"><a href=\"https://en.wikipedia.org/wiki/User:MattWade/ImageAttribution\" title=\"en:User:MattWade/ImageAttribution\"><img src=\"https://upload.wikimedia.org/wikipedia/commons/thumb/e/e5/CC_BY-SA_icon.svg/60px-CC_BY-SA_icon.svg.png\" decoding=\"async\" width=\"50\" height=\"18\" class=\"mw-file-element\" srcset=\"https://upload.wikimedia.org/wikipedia/commons/thumb/e/e5/CC_BY-SA_icon.svg/120px-CC_BY-SA_icon.svg.png 2x\" data-file-width=\"88\" data-file-height=\"31\"></a></span> This image is <b>protected by copyright</b>! If you would like to use it, please read <a href=\"https://en.wikipedia.org/wiki/User:MattWade/ImageAttribution\" class=\"extiw\" title=\"en:User:MattWade/ImageAttribution\">this</a> first. <span typeof=\"mw:File\"><a href=\"https://en.wikipedia.org/wiki/User:MattWade/ImageAttribution\" title=\"en:User:MattWade/ImageAttribution\"><img src=\"https://upload.wikimedia.org/wikipedia/commons/thumb/a/a3/Cc.logo.circle.svg/20px-Cc.logo.circle.svg.png\" decoding=\"async\" width=\"20\" height=\"20\" class=\"mw-file-element\" srcset=\"https://upload.wikimedia.org/wikipedia/commons/thumb/a/a3/Cc.logo.circle.svg/40px-Cc.logo.circle.svg.png 2x\" data-file-width=\"64\" data-file-height=\"64\"></a></span>\n</p>\n</td></tr></tbody></table>",
    "artistText": "This image or media was taken or created by Matt H. Wade. To see his entire portfolio, click here.@thatmattwade This image is protected by copyright! If you would like to use it, please read this first.",
    "avifPath": "/state-images/new-york.avif",
    "jpgPath": "/state-images/new-york.jpg",
    "finalWidth": 1280,
    "finalHeight": 760,
    "avifBytes": 120871,
    "jpgBytes": 171509
  },
  {
    "slug": "north-carolina",
    "name": "North Carolina",
    "code": "NC",
    "wikipediaTitle": "North Carolina State Capitol",
    "wikipediaUrl": "https://en.wikipedia.org/wiki/North_Carolina_State_Capitol",
    "imageUrl": "https://upload.wikimedia.org/wikipedia/commons/0/04/2015_North_Carolina_State_Capitol.JPG",
    "imageWidth": 4608,
    "imageHeight": 3456,
    "mime": "image/jpeg",
    "commonsFileTitle": "File:2015 North Carolina State Capitol.JPG",
    "commonsFileUrl": "https://commons.wikimedia.org/wiki/File:2015_North_Carolina_State_Capitol.JPG",
    "licenseShort": "CC BY-SA 4.0",
    "licenseUrl": "https://creativecommons.org/licenses/by-sa/4.0",
    "artistHtml": "<a href=\"//commons.wikimedia.org/wiki/User:Farragutful\" title=\"User:Farragutful\">Farragutful</a>",
    "artistText": "Farragutful",
    "avifPath": "/state-images/north-carolina.avif",
    "jpgPath": "/state-images/north-carolina.jpg",
    "finalWidth": 1280,
    "finalHeight": 960,
    "avifBytes": 67630,
    "jpgBytes": 131003
  },
  {
    "slug": "north-dakota",
    "name": "North Dakota",
    "code": "ND",
    "wikipediaTitle": "North Dakota State Capitol",
    "wikipediaUrl": "https://en.wikipedia.org/wiki/North_Dakota_State_Capitol",
    "imageUrl": "https://upload.wikimedia.org/wikipedia/commons/8/8b/North_Dakota_State_Capitol.jpg",
    "imageWidth": 7278,
    "imageHeight": 4853,
    "mime": "image/jpeg",
    "commonsFileTitle": "File:North Dakota State Capitol.jpg",
    "commonsFileUrl": "https://commons.wikimedia.org/wiki/File:North_Dakota_State_Capitol.jpg",
    "licenseShort": "CC BY 4.0",
    "licenseUrl": "https://creativecommons.org/licenses/by/4.0",
    "artistHtml": "<a href=\"//commons.wikimedia.org/wiki/User:Quintin_Soloviev\" title=\"User:Quintin Soloviev\">Quintin Soloviev</a>",
    "artistText": "Quintin Soloviev",
    "avifPath": "/state-images/north-dakota.avif",
    "jpgPath": "/state-images/north-dakota.jpg",
    "finalWidth": 1280,
    "finalHeight": 854,
    "avifBytes": 65988,
    "jpgBytes": 134188
  },
  {
    "slug": "ohio",
    "name": "Ohio",
    "code": "OH",
    "wikipediaTitle": "Ohio Statehouse",
    "wikipediaUrl": "https://en.wikipedia.org/wiki/Ohio_Statehouse",
    "imageUrl": "https://upload.wikimedia.org/wikipedia/commons/a/a6/Ohio_Statehouse_exterior.jpg",
    "imageWidth": 4869,
    "imageHeight": 3052,
    "mime": "image/jpeg",
    "commonsFileTitle": "File:Ohio Statehouse exterior.jpg",
    "commonsFileUrl": "https://commons.wikimedia.org/wiki/File:Ohio_Statehouse_exterior.jpg",
    "licenseShort": "CC BY-SA 4.0",
    "licenseUrl": "https://creativecommons.org/licenses/by-sa/4.0",
    "artistHtml": "<a href=\"//commons.wikimedia.org/wiki/User:%E2%B1%AE\" title=\"User:Ɱ\">Ɱ</a>",
    "artistText": "Ɱ",
    "avifPath": "/state-images/ohio.avif",
    "jpgPath": "/state-images/ohio.jpg",
    "finalWidth": 1280,
    "finalHeight": 802,
    "avifBytes": 52831,
    "jpgBytes": 110713
  },
  {
    "slug": "oklahoma",
    "name": "Oklahoma",
    "code": "OK",
    "wikipediaTitle": "Oklahoma State Capitol",
    "wikipediaUrl": "https://en.wikipedia.org/wiki/Oklahoma_State_Capitol",
    "imageUrl": "https://upload.wikimedia.org/wikipedia/commons/0/03/North_fa%C3%A7ade_of_the_Oklahoma_State_Capitol.jpg",
    "imageWidth": 2023,
    "imageHeight": 1350,
    "mime": "image/jpeg",
    "commonsFileTitle": "File:North façade of the Oklahoma State Capitol.jpg",
    "commonsFileUrl": "https://commons.wikimedia.org/wiki/File:North_fa%C3%A7ade_of_the_Oklahoma_State_Capitol.jpg",
    "licenseShort": "CC0",
    "licenseUrl": "http://creativecommons.org/publicdomain/zero/1.0/deed.en",
    "artistHtml": "Oklahoma Legislative Services Bureau",
    "artistText": "Oklahoma Legislative Services Bureau",
    "avifPath": "/state-images/oklahoma.avif",
    "jpgPath": "/state-images/oklahoma.jpg",
    "finalWidth": 1280,
    "finalHeight": 854,
    "avifBytes": 51477,
    "jpgBytes": 105462
  },
  {
    "slug": "oregon",
    "name": "Oregon",
    "code": "OR",
    "wikipediaTitle": "Oregon State Capitol",
    "wikipediaUrl": "https://en.wikipedia.org/wiki/Oregon_State_Capitol",
    "imageUrl": "https://upload.wikimedia.org/wikipedia/commons/c/ce/Oregon_State_Capitol_1.jpg",
    "imageWidth": 2200,
    "imageHeight": 1667,
    "mime": "image/jpeg",
    "commonsFileTitle": "File:Oregon State Capitol 1.jpg",
    "commonsFileUrl": "https://commons.wikimedia.org/wiki/File:Oregon_State_Capitol_1.jpg",
    "licenseShort": "Public domain",
    "licenseUrl": null,
    "artistHtml": "<a href=\"//commons.wikimedia.org/wiki/User:Aboutmovies\" title=\"User:Aboutmovies\">M.O. Stevens</a>",
    "artistText": "M.O. Stevens",
    "avifPath": "/state-images/oregon.avif",
    "jpgPath": "/state-images/oregon.jpg",
    "finalWidth": 1280,
    "finalHeight": 970,
    "avifBytes": 40948,
    "jpgBytes": 99710
  },
  {
    "slug": "pennsylvania",
    "name": "Pennsylvania",
    "code": "PA",
    "wikipediaTitle": "Pennsylvania State Capitol",
    "wikipediaUrl": "https://en.wikipedia.org/wiki/Pennsylvania_State_Capitol",
    "imageUrl": "https://upload.wikimedia.org/wikipedia/commons/4/43/Flying_the_Pride_Flag_over_the_Capitol_%2850035197647%29.jpg",
    "imageWidth": 3000,
    "imageHeight": 1688,
    "mime": "image/jpeg",
    "commonsFileTitle": "File:Flying the Pride Flag over the Capitol (50035197647).jpg",
    "commonsFileUrl": "https://commons.wikimedia.org/wiki/File:Flying_the_Pride_Flag_over_the_Capitol_(50035197647).jpg",
    "licenseShort": "CC BY 2.0",
    "licenseUrl": "https://creativecommons.org/licenses/by/2.0",
    "artistHtml": "<a rel=\"nofollow\" class=\"external text\" href=\"https://www.flickr.com/people/130921112@N07\">Governor Tom Wolf</a> from Harrisburg, PA",
    "artistText": "Governor Tom Wolf from Harrisburg, PA",
    "avifPath": "/state-images/pennsylvania.avif",
    "jpgPath": "/state-images/pennsylvania.jpg",
    "finalWidth": 1280,
    "finalHeight": 720,
    "avifBytes": 73966,
    "jpgBytes": 117389
  },
  {
    "slug": "rhode-island",
    "name": "Rhode Island",
    "code": "RI",
    "wikipediaTitle": "Rhode Island State House",
    "wikipediaUrl": "https://en.wikipedia.org/wiki/Rhode_Island_State_House",
    "imageUrl": "https://upload.wikimedia.org/wikipedia/commons/4/44/2021_Rhode_Island_State_House_from_east.jpg",
    "imageWidth": 3939,
    "imageHeight": 3013,
    "mime": "image/jpeg",
    "commonsFileTitle": "File:2021 Rhode Island State House from east.jpg",
    "commonsFileUrl": "https://commons.wikimedia.org/wiki/File:2021_Rhode_Island_State_House_from_east.jpg",
    "licenseShort": "CC BY-SA 4.0",
    "licenseUrl": "https://creativecommons.org/licenses/by-sa/4.0",
    "artistHtml": "<a href=\"//commons.wikimedia.org/wiki/User:Beyond_My_Ken\" class=\"mw-redirect\" title=\"User:Beyond My Ken\">Beyond My Ken</a>",
    "artistText": "Beyond My Ken",
    "avifPath": "/state-images/rhode-island.avif",
    "jpgPath": "/state-images/rhode-island.jpg",
    "finalWidth": 1280,
    "finalHeight": 979,
    "avifBytes": 115358,
    "jpgBytes": 177699
  },
  {
    "slug": "south-carolina",
    "name": "South Carolina",
    "code": "SC",
    "wikipediaTitle": "South Carolina State House",
    "wikipediaUrl": "https://en.wikipedia.org/wiki/South_Carolina_State_House",
    "imageUrl": "https://upload.wikimedia.org/wikipedia/commons/5/50/South_Carolina_State_House.JPG",
    "imageWidth": 3264,
    "imageHeight": 2448,
    "mime": "image/jpeg",
    "commonsFileTitle": "File:South Carolina State House.JPG",
    "commonsFileUrl": "https://commons.wikimedia.org/wiki/File:South_Carolina_State_House.JPG",
    "licenseShort": "CC BY-SA 3.0",
    "licenseUrl": "https://creativecommons.org/licenses/by-sa/3.0",
    "artistHtml": "<a href=\"//commons.wikimedia.org/w/index.php?title=User:HaloMasterMind&amp;action=edit&amp;redlink=1\" class=\"new\" title=\"User:HaloMasterMind (page does not exist)\">HaloMasterMind</a>",
    "artistText": "HaloMasterMind",
    "avifPath": "/state-images/south-carolina.avif",
    "jpgPath": "/state-images/south-carolina.jpg",
    "finalWidth": 1280,
    "finalHeight": 960,
    "avifBytes": 106752,
    "jpgBytes": 177952
  },
  {
    "slug": "south-dakota",
    "name": "South Dakota",
    "code": "SD",
    "wikipediaTitle": "South Dakota State Capitol",
    "wikipediaUrl": "https://en.wikipedia.org/wiki/South_Dakota_State_Capitol",
    "imageUrl": "https://upload.wikimedia.org/wikipedia/commons/2/29/South_Dakota_State_Capitol.jpg",
    "imageWidth": 4032,
    "imageHeight": 3024,
    "mime": "image/jpeg",
    "commonsFileTitle": "File:South Dakota State Capitol.jpg",
    "commonsFileUrl": "https://commons.wikimedia.org/wiki/File:South_Dakota_State_Capitol.jpg",
    "licenseShort": "CC BY-SA 4.0",
    "licenseUrl": "https://creativecommons.org/licenses/by-sa/4.0",
    "artistHtml": "<a href=\"//commons.wikimedia.org/wiki/User:WeaponizingArchitecture\" title=\"User:WeaponizingArchitecture\">WeaponizingArchitecture</a>",
    "artistText": "WeaponizingArchitecture",
    "avifPath": "/state-images/south-dakota.avif",
    "jpgPath": "/state-images/south-dakota.jpg",
    "finalWidth": 1280,
    "finalHeight": 960,
    "avifBytes": 146675,
    "jpgBytes": 203337
  },
  {
    "slug": "tennessee",
    "name": "Tennessee",
    "code": "TN",
    "wikipediaTitle": "Tennessee State Capitol",
    "wikipediaUrl": "https://en.wikipedia.org/wiki/Tennessee_State_Capitol",
    "imageUrl": "https://upload.wikimedia.org/wikipedia/commons/a/ae/Tennessee_State_Capitol_2022f.jpg",
    "imageWidth": 6240,
    "imageHeight": 4160,
    "mime": "image/jpeg",
    "commonsFileTitle": "File:Tennessee State Capitol 2022f.jpg",
    "commonsFileUrl": "https://commons.wikimedia.org/wiki/File:Tennessee_State_Capitol_2022f.jpg",
    "licenseShort": "CC BY-SA 4.0",
    "licenseUrl": "https://creativecommons.org/licenses/by-sa/4.0",
    "artistHtml": "<a href=\"//commons.wikimedia.org/wiki/User:Antony-22\" title=\"User:Antony-22\">Antony-22</a>",
    "artistText": "Antony-22",
    "avifPath": "/state-images/tennessee.avif",
    "jpgPath": "/state-images/tennessee.jpg",
    "finalWidth": 1280,
    "finalHeight": 853,
    "avifBytes": 55453,
    "jpgBytes": 123434
  },
  {
    "slug": "texas",
    "name": "Texas",
    "code": "TX",
    "wikipediaTitle": "Texas State Capitol",
    "wikipediaUrl": "https://en.wikipedia.org/wiki/Texas_State_Capitol",
    "imageUrl": "https://upload.wikimedia.org/wikipedia/commons/d/df/TexasStateCapitol-2010-01.JPG",
    "imageWidth": 2673,
    "imageHeight": 1782,
    "mime": "image/jpeg",
    "commonsFileTitle": "File:TexasStateCapitol-2010-01.JPG",
    "commonsFileUrl": "https://commons.wikimedia.org/wiki/File:TexasStateCapitol-2010-01.JPG",
    "licenseShort": "CC BY 3.0",
    "licenseUrl": "https://creativecommons.org/licenses/by/3.0",
    "artistHtml": "<a href=\"//commons.wikimedia.org/wiki/User:LoneStarMike\" title=\"User:LoneStarMike\">LoneStarMike</a>",
    "artistText": "LoneStarMike",
    "avifPath": "/state-images/texas.avif",
    "jpgPath": "/state-images/texas.jpg",
    "finalWidth": 1280,
    "finalHeight": 853,
    "avifBytes": 125859,
    "jpgBytes": 178436
  },
  {
    "slug": "utah",
    "name": "Utah",
    "code": "UT",
    "wikipediaTitle": "Utah State Capitol",
    "wikipediaUrl": "https://en.wikipedia.org/wiki/Utah_State_Capitol",
    "imageUrl": "https://upload.wikimedia.org/wikipedia/commons/3/30/Utah_State_Capitol%2C_Salt_Lake_City_%287631480380%29_%28cropped%29.jpg",
    "imageWidth": 4693,
    "imageHeight": 2347,
    "mime": "image/jpeg",
    "commonsFileTitle": "File:Utah State Capitol, Salt Lake City (7631480380) (cropped).jpg",
    "commonsFileUrl": "https://commons.wikimedia.org/wiki/File:Utah_State_Capitol,_Salt_Lake_City_(7631480380)_(cropped).jpg",
    "licenseShort": "CC BY-SA 2.0",
    "licenseUrl": "https://creativecommons.org/licenses/by-sa/2.0",
    "artistHtml": "<a rel=\"nofollow\" class=\"external text\" href=\"https://www.flickr.com/people/40165565@N03\">Andrew Smith</a> from Seattle, WA, USA",
    "artistText": "Andrew Smith from Seattle, WA, USA",
    "avifPath": "/state-images/utah.avif",
    "jpgPath": "/state-images/utah.jpg",
    "finalWidth": 1280,
    "finalHeight": 640,
    "avifBytes": 47475,
    "jpgBytes": 87989
  },
  {
    "slug": "vermont",
    "name": "Vermont",
    "code": "VT",
    "wikipediaTitle": "Vermont State House",
    "wikipediaUrl": "https://en.wikipedia.org/wiki/Vermont_State_House",
    "imageUrl": "https://upload.wikimedia.org/wikipedia/commons/1/1c/Vermont_State_Capitol_May_2024.jpg",
    "imageWidth": 3600,
    "imageHeight": 3600,
    "mime": "image/jpeg",
    "commonsFileTitle": "File:Vermont State Capitol May 2024.jpg",
    "commonsFileUrl": "https://commons.wikimedia.org/wiki/File:Vermont_State_Capitol_May_2024.jpg",
    "licenseShort": "CC BY 4.0",
    "licenseUrl": "https://creativecommons.org/licenses/by/4.0",
    "artistHtml": "<a href=\"//commons.wikimedia.org/wiki/User:Kzirkel\" title=\"User:Kzirkel\">Kenneth C. Zirkel</a>",
    "artistText": "Kenneth C. Zirkel",
    "avifPath": "/state-images/vermont.avif",
    "jpgPath": "/state-images/vermont.jpg",
    "finalWidth": 1280,
    "finalHeight": 1280,
    "avifBytes": 159159,
    "jpgBytes": 260874
  },
  {
    "slug": "virginia",
    "name": "Virginia",
    "code": "VA",
    "wikipediaTitle": "Virginia State Capitol",
    "wikipediaUrl": "https://en.wikipedia.org/wiki/Virginia_State_Capitol",
    "imageUrl": "https://upload.wikimedia.org/wikipedia/commons/6/69/MJK50147_Virginia_State_Capitol.jpg",
    "imageWidth": 5616,
    "imageHeight": 2407,
    "mime": "image/jpeg",
    "commonsFileTitle": "File:MJK50147 Virginia State Capitol.jpg",
    "commonsFileUrl": "https://commons.wikimedia.org/wiki/File:MJK50147_Virginia_State_Capitol.jpg",
    "licenseShort": "CC BY-SA 3.0",
    "licenseUrl": "https://creativecommons.org/licenses/by-sa/3.0",
    "artistHtml": "<a href=\"//commons.wikimedia.org/wiki/User:Martin_Kraft\" title=\"User:Martin Kraft\">Martin Kraft</a>",
    "artistText": "Martin Kraft",
    "avifPath": "/state-images/virginia.avif",
    "jpgPath": "/state-images/virginia.jpg",
    "finalWidth": 1280,
    "finalHeight": 548,
    "avifBytes": 36303,
    "jpgBytes": 78086
  },
  {
    "slug": "washington",
    "name": "Washington",
    "code": "WA",
    "wikipediaTitle": "Washington State Capitol",
    "wikipediaUrl": "https://en.wikipedia.org/wiki/Washington_State_Capitol",
    "imageUrl": "https://upload.wikimedia.org/wikipedia/commons/2/23/MK03168_Washington_State_Capitol_%28Olympia%29.jpg",
    "imageWidth": 3443,
    "imageHeight": 4591,
    "mime": "image/jpeg",
    "commonsFileTitle": "File:MK03168 Washington State Capitol (Olympia).jpg",
    "commonsFileUrl": "https://commons.wikimedia.org/wiki/File:MK03168_Washington_State_Capitol_(Olympia).jpg",
    "licenseShort": "CC BY-SA 4.0",
    "licenseUrl": "https://creativecommons.org/licenses/by-sa/4.0",
    "artistHtml": "Martin Kraft",
    "artistText": "Martin Kraft",
    "avifPath": "/state-images/washington.avif",
    "jpgPath": "/state-images/washington.jpg",
    "finalWidth": 960,
    "finalHeight": 1280,
    "avifBytes": 71344,
    "jpgBytes": 144893
  },
  {
    "slug": "west-virginia",
    "name": "West Virginia",
    "code": "WV",
    "wikipediaTitle": "West Virginia State Capitol",
    "wikipediaUrl": "https://en.wikipedia.org/wiki/West_Virginia_State_Capitol",
    "imageUrl": "https://upload.wikimedia.org/wikipedia/commons/0/03/West_Virginia_State_Capitol%2C_Charleston%2C_WV%2C_US_%2815%29.jpg",
    "imageWidth": 6000,
    "imageHeight": 4000,
    "mime": "image/jpeg",
    "commonsFileTitle": "File:West Virginia State Capitol, Charleston, WV, US (15).jpg",
    "commonsFileUrl": "https://commons.wikimedia.org/wiki/File:West_Virginia_State_Capitol,_Charleston,_WV,_US_(15).jpg",
    "licenseShort": "CC BY-SA 3.0",
    "licenseUrl": "https://creativecommons.org/licenses/by-sa/3.0",
    "artistHtml": "<a href=\"//commons.wikimedia.org/wiki/User:Bubba73\" title=\"User:Bubba73\">Bubba73</a>",
    "artistText": "Bubba73",
    "avifPath": "/state-images/west-virginia.avif",
    "jpgPath": "/state-images/west-virginia.jpg",
    "finalWidth": 1280,
    "finalHeight": 853,
    "avifBytes": 144654,
    "jpgBytes": 187851
  },
  {
    "slug": "wisconsin",
    "name": "Wisconsin",
    "code": "WI",
    "wikipediaTitle": "Wisconsin State Capitol",
    "wikipediaUrl": "https://en.wikipedia.org/wiki/Wisconsin_State_Capitol",
    "imageUrl": "https://upload.wikimedia.org/wikipedia/commons/6/60/Wisconsin_State_Capitol_Building_6.jpg",
    "imageWidth": 4000,
    "imageHeight": 3000,
    "mime": "image/jpeg",
    "commonsFileTitle": "File:Wisconsin State Capitol Building 6.jpg",
    "commonsFileUrl": "https://commons.wikimedia.org/wiki/File:Wisconsin_State_Capitol_Building_6.jpg",
    "licenseShort": "CC0",
    "licenseUrl": "http://creativecommons.org/publicdomain/zero/1.0/deed.en",
    "artistHtml": "<a href=\"//commons.wikimedia.org/wiki/User:Wikideas1\" title=\"User:Wikideas1\">Wikideas1</a>",
    "artistText": "Wikideas1",
    "avifPath": "/state-images/wisconsin.avif",
    "jpgPath": "/state-images/wisconsin.jpg",
    "finalWidth": 1280,
    "finalHeight": 960,
    "avifBytes": 149829,
    "jpgBytes": 223579
  },
  {
    "slug": "wyoming",
    "name": "Wyoming",
    "code": "WY",
    "wikipediaTitle": "Wyoming State Capitol",
    "wikipediaUrl": "https://en.wikipedia.org/wiki/Wyoming_State_Capitol",
    "imageUrl": "https://upload.wikimedia.org/wikipedia/commons/a/a9/DSCN5263_cheyennewyomingcapitolfront_e.jpg",
    "imageWidth": 534,
    "imageHeight": 709,
    "mime": "image/jpeg",
    "commonsFileTitle": "File:DSCN5263 cheyennewyomingcapitolfront e.jpg",
    "commonsFileUrl": "https://commons.wikimedia.org/wiki/File:DSCN5263_cheyennewyomingcapitolfront_e.jpg",
    "licenseShort": "CC BY-SA 3.0",
    "licenseUrl": "http://creativecommons.org/licenses/by-sa/3.0/",
    "artistHtml": "<a href=\"//commons.wikimedia.org/w/index.php?title=User:Decumanus&amp;action=edit&amp;redlink=1\" class=\"new\" title=\"User:Decumanus (page does not exist)\">Matthew Trump</a>",
    "artistText": "Matthew Trump",
    "avifPath": "/state-images/wyoming.avif",
    "jpgPath": "/state-images/wyoming.jpg",
    "finalWidth": 534,
    "finalHeight": 709,
    "avifBytes": 58788,
    "jpgBytes": 79327
  },
  {
    "slug": "puerto-rico",
    "name": "Puerto Rico",
    "code": "PR",
    "wikipediaTitle": "Old San Juan",
    "wikipediaUrl": "https://en.wikipedia.org/wiki/Old_San_Juan",
    "imageUrl": "https://upload.wikimedia.org/wikipedia/commons/f/fa/Castillo_San_Felipe_del_Morro_aerial%2C_May_2024_-_01.jpg",
    "imageWidth": 4032,
    "imageHeight": 2268,
    "mime": "image/jpeg",
    "commonsFileTitle": "File:Castillo San Felipe del Morro aerial, May 2024 - 01.jpg",
    "commonsFileUrl": "https://commons.wikimedia.org/wiki/File:Castillo_San_Felipe_del_Morro_aerial,_May_2024_-_01.jpg",
    "licenseShort": "CC BY 4.0",
    "licenseUrl": "https://creativecommons.org/licenses/by/4.0",
    "artistHtml": "<a href=\"//commons.wikimedia.org/w/index.php?title=User:Druemdach&amp;action=edit&amp;redlink=1\" class=\"new\" title=\"User:Druemdach (page does not exist)\">Nils Huenerfuerst</a> <span class=\"mw-valign-text-top noprint\" typeof=\"mw:File/Frameless\"><a href=\"//commons.wikimedia.org/wiki/File:Castillo_San_Felipe_del_Morro_aerial,_May_2024_-_01.jpg#P170\" title=\"Edit this at Structured Data on Commons\"><img alt=\"Edit this at Structured Data on Commons\" src=\"https://upload.wikimedia.org/wikipedia/commons/thumb/8/8a/OOjs_UI_icon_edit-ltr-progressive.svg/20px-OOjs_UI_icon_edit-ltr-progressive.svg.png\" decoding=\"async\" width=\"10\" height=\"10\" class=\"mw-file-element\" data-file-width=\"20\" data-file-height=\"20\"></a></span>",
    "artistText": "Nils Huenerfuerst",
    "avifPath": "/state-images/puerto-rico.avif",
    "jpgPath": "/state-images/puerto-rico.jpg",
    "finalWidth": 1280,
    "finalHeight": 720,
    "avifBytes": 121088,
    "jpgBytes": 160714
  },
  {
    "slug": "guam",
    "name": "Guam",
    "code": "GU",
    "wikipediaTitle": "Tumon, Guam",
    "wikipediaUrl": "https://en.wikipedia.org/wiki/Tumon%2C_Guam",
    "imageUrl": "https://upload.wikimedia.org/wikipedia/commons/6/60/Tumon_Bay_-_panoramio_-_Scott_Cameron.jpg",
    "imageWidth": 1080,
    "imageHeight": 541,
    "mime": "image/jpeg",
    "commonsFileTitle": "File:Tumon Bay - panoramio - Scott Cameron.jpg",
    "commonsFileUrl": "https://commons.wikimedia.org/wiki/File:Tumon_Bay_-_panoramio_-_Scott_Cameron.jpg",
    "licenseShort": "CC BY 3.0",
    "licenseUrl": "https://creativecommons.org/licenses/by/3.0",
    "artistHtml": "<a rel=\"nofollow\" class=\"external text\" href=\"https://web.archive.org/web/20161017221532/http://www.panoramio.com/user/57605?with_photo_id=47405049\">Scott Cameron</a>",
    "artistText": "Scott Cameron",
    "avifPath": "/state-images/guam.avif",
    "jpgPath": "/state-images/guam.jpg",
    "finalWidth": 1080,
    "finalHeight": 541,
    "avifBytes": 36813,
    "jpgBytes": 75078
  },
  {
    "slug": "virgin-islands",
    "name": "Virgin Islands",
    "code": "VI",
    "wikipediaTitle": "Charlotte Amalie, U.S. Virgin Islands",
    "wikipediaUrl": "https://en.wikipedia.org/wiki/Charlotte_Amalie%2C_U.S._Virgin_Islands",
    "imageUrl": "https://upload.wikimedia.org/wikipedia/commons/a/ac/FortChristian.jpg",
    "imageWidth": 4032,
    "imageHeight": 3024,
    "mime": "image/jpeg",
    "commonsFileTitle": "File:FortChristian.jpg",
    "commonsFileUrl": "https://commons.wikimedia.org/wiki/File:FortChristian.jpg",
    "licenseShort": "CC BY-SA 4.0",
    "licenseUrl": "https://creativecommons.org/licenses/by-sa/4.0",
    "artistHtml": "<a href=\"//commons.wikimedia.org/w/index.php?title=User:Gruepig&amp;action=edit&amp;redlink=1\" class=\"new\" title=\"User:Gruepig (page does not exist)\">Gruepig</a>",
    "artistText": "Gruepig",
    "avifPath": "/state-images/virgin-islands.avif",
    "jpgPath": "/state-images/virgin-islands.jpg",
    "finalWidth": 1280,
    "finalHeight": 960,
    "avifBytes": 90992,
    "jpgBytes": 150805
  }
]